MANIFEST.in
README.md
setup.py
pyharfbuzz/__init__.py
pyharfbuzz/_compat.py
pyharfbuzz/harfbuzz.c
pyharfbuzz.egg-info/PKG-INFO
pyharfbuzz.egg-info/SOURCES.txt
pyharfbuzz.egg-info/dependency_links.txt
pyharfbuzz.egg-info/top_level.txt