Metadata-Version: 1.0
Name: pyharfbuzz
Version: 0.2.2
Summary: Python binding for harfbuzz an OpenType text shaping.
Home-page: https://github.com/RevengeComing/pyharfbuzz
Author: Sepehr Hamzehlouy
Author-email: s.hamzelooy@gmail.com
License: MIT
Platform: UNKNOWN
